{
  "search_date": "2026-06-28T22:05:49.662222",
  "total_results": 16,
  "results": [
    {
      "platform": "Mercari Japan",
      "game": "Zelda",
      "condition": "sealed",
      "title": "【未開封品】ゼルダの伝説1 ファミコンソフト",
      "price": "N/A",
      "price_raw": null,
      "currency": "JPY",
      "link": "https://jp.mercari.com/item/m52160143551",
      "listing_type": "buy_now",
      "search_query": "ファミコン 未開封 ゼルダの伝説"
    },
    {
      "platform": "Mercari Japan",
      "game": "Zelda",
      "condition": "sealed",
      "title": "【未開封品】ファミコン★ゼルダの伝説 1 HVC-ZL★",
      "price": "N/A",
      "price_raw": null,
      "currency": "JPY",
      "link": "https://jp.mercari.com/item/m97161856386",
      "listing_type": "buy_now",
      "search_query": "ファミコン 未開封 ゼルダの伝説"
    },
    {
      "platform": "Mercari Japan",
      "game": "Zelda",
      "condition": "sealed",
      "title": "ゼルダの伝説　(未開封レベル) ファミコン ディスクシステム",
      "price": "N/A",
      "price_raw": null,
      "currency": "JPY",
      "link": "https://jp.mercari.com/item/m83181387372",
      "listing_type": "buy_now",
      "search_query": "ファミコン 未開封 ゼルダの伝説"
    },
    {
      "platform": "Mercari Japan",
      "game": "Zelda",
      "condition": "sealed",
      "title": "【新品 未開封】ファミコン ディスクシステム　ゼルダの伝説",
      "price": "N/A",
      "price_raw": null,
      "currency": "JPY",
      "link": "https://jp.mercari.com/item/m31178886374",
      "listing_type": "buy_now",
      "search_query": "ファミコン 未開封 ゼルダの伝説"
    },
    {
      "platform": "Mercari Japan",
      "game": "Mario",
      "condition": "sealed",
      "title": "250　未開封　スーパーマリオブラザーズ　ファミコンディスクシステム",
      "price": "N/A",
      "price_raw": null,
      "currency": "JPY",
      "link": "https://jp.mercari.com/item/m46521966454",
      "listing_type": "buy_now",
      "search_query": "ファミコン 未開封 スーパーマリオブラザーズ"
    },
    {
      "platform": "Mercari Japan",
      "game": "Mario",
      "condition": "sealed",
      "title": "新品未開封品ファミコンミニ マリオブラザーズ GBA",
      "price": "N/A",
      "price_raw": null,
      "currency": "JPY",
      "link": "https://jp.mercari.com/item/m69071131579",
      "listing_type": "buy_now",
      "search_query": "ファミコン 未開封 マリオ"
    },
    {
      "platform": "Mercari Japan",
      "game": "Dragon Quest",
      "condition": "sealed",
      "title": "315　未開封　ドラゴンクエスト4　ドラゴンクエストⅣ　ファミコン",
      "price": "N/A",
      "price_raw": null,
      "currency": "JPY",
      "link": "https://jp.mercari.com/item/m73898869987",
      "listing_type": "buy_now",
      "search_query": "ファミコン 未開封 ドラゴンクエスト"
    },
    {
      "platform": "Mercari Japan",
      "game": "Dragon Quest",
      "condition": "sealed",
      "title": "未開封　ドラゴンクエストⅣ　ドラゴンクエスト4 ファミコン奥義大全書　　攻略本",
      "price": "N/A",
      "price_raw": null,
      "currency": "JPY",
      "link": "https://jp.mercari.com/item/m48067979590",
      "listing_type": "buy_now",
      "search_query": "ファミコン 未開封 ドラゴンクエスト"
    },
    {
      "platform": "Mercari Japan",
      "game": "Dragon Quest",
      "condition": "sealed",
      "title": "ドラゴンクエストⅣ　導かれし者たち　ファミコン奥義大全書　初版　袋とじ未開封",
      "price": "N/A",
      "price_raw": null,
      "currency": "JPY",
      "link": "https://jp.mercari.com/item/m52295933949",
      "listing_type": "buy_now",
      "search_query": "ファミコン 未開封 ドラゴンクエスト"
    },
    {
      "platform": "Mercari Japan",
      "game": "Final Fantasy",
      "condition": "sealed",
      "title": "【新品未開封/凹みあり】ファイナルファンタジー3 ファミコンソフト任天堂",
      "price": "N/A",
      "price_raw": null,
      "currency": "JPY",
      "link": "https://jp.mercari.com/item/m84258859860",
      "listing_type": "buy_now",
      "search_query": "ファミコン 未開封 ファイナルファンタジー"
    },
    {
      "platform": "Mercari Japan",
      "game": "Final Fantasy",
      "condition": "sealed",
      "title": "【新品未開封/超美品】ファイナルファンタジー2 ファミコンソフトNintendo",
      "price": "N/A",
      "price_raw": null,
      "currency": "JPY",
      "link": "https://jp.mercari.com/item/m44854227412",
      "listing_type": "buy_now",
      "search_query": "ファミコン 未開封 ファイナルファンタジー"
    },
    {
      "platform": "Buyee",
      "game": "Zelda",
      "condition": "sealed",
      "title": "ファミコン 新品未使用未開封　ゼルダの伝説1",
      "price": "現在の価格\n49,999円 (425.00シンガポールドル)\n即決価格\n50,000円 (425.00シンガポールドル)",
      "price_raw": null,
      "currency": "JPY",
      "link": "https://buyee.jp/item/jdirectitems/auction/w1229744434?conversionType=jdirectitems_auction_DirectSearch",
      "listing_type": "auction",
      "search_query": "ファミコン 未開封 ゼルダの伝説"
    },
    {
      "platform": "Buyee",
      "game": "Zelda",
      "condition": "sealed",
      "title": "貴重【未開封】ファミコン＆カセット インボックスセット フルコンプリート ５種　スーパーマリオブラザーズ ゼルダの伝説 ドクターマリオ",
      "price": "現在の価格\n14,999円 (127.50シンガポールドル)\n即決価格\n19,999円 (170.00シンガポールドル)",
      "price_raw": null,
      "currency": "JPY",
      "link": "https://buyee.jp/item/jdirectitems/auction/l1233112075?conversionType=jdirectitems_auction_DirectSearch",
      "listing_type": "auction",
      "search_query": "ファミコン 未開封 ゼルダの伝説"
    },
    {
      "platform": "Buyee",
      "game": "Mario",
      "condition": "sealed",
      "title": "送料安 新品未開封 ツクダ スーパーマリオ ファミコン ゆ太郎 3点まとめて",
      "price": "現在の価格\n2,650円 (22.53シンガポールドル)\n即決価格\n2,650円 (22.53シンガポールドル)",
      "price_raw": null,
      "currency": "JPY",
      "link": "https://buyee.jp/item/jdirectitems/auction/j1233638147?conversionType=jdirectitems_auction_DirectSearch",
      "listing_type": "auction",
      "search_query": "ファミコン 未開封 マリオ"
    },
    {
      "platform": "Buyee",
      "game": "Dragon Quest",
      "condition": "sealed",
      "title": "【新品未開封】ドラゴンクエストⅣ 導かれし者たち　コレクションケース付き　ファミコン　FC　ファミリーコンピューター　ドラクエ　DQⅣ",
      "price": "現在の価格\n18,000円 (153.00シンガポールドル)\n即決価格\n18,000円 (153.00シンガポールドル)",
      "price_raw": null,
      "currency": "JPY",
      "link": "https://buyee.jp/item/jdirectitems/auction/m1200289349?conversionType=jdirectitems_auction_DirectSearch",
      "listing_type": "auction",
      "search_query": "ファミコン 未開封 ドラゴンクエスト"
    },
    {
      "platform": "Buyee",
      "game": "Final Fantasy",
      "condition": "sealed",
      "title": "【新品未開封・極上品】FC ファミコンソフト ファイナルファンタジー2 スクウェア 1円スタート 非常に綺麗な新品 当時物",
      "price": "現在の価格\n31円 (0.27シンガポールドル)",
      "price_raw": null,
      "currency": "JPY",
      "link": "https://buyee.jp/item/jdirectitems/auction/w1235093232?conversionType=jdirectitems_auction_DirectSearch",
      "listing_type": "auction",
      "search_query": "ファミコン 未開封 ファイナルファンタジー"
    }
  ]
}